letesend/__init__.py
letesend/letesend.py
letesend-0.2.dist-info/LICENSE.txt
letesend-0.2.dist-info/METADATA
letesend-0.2.dist-info/WHEEL
letesend-0.2.dist-info/top_level.txt
letesend-0.2.dist-info/RECORD
