Metadata-Version: 2.1
Name: letesend
Version: 0.2
Summary: Letesend sdk for sending and monitoring SMS
Home-page: https://github.com/letesend/python
Author: Letesend
Author-email: support@letesend.com
License: MIT
Keywords: letesend,letesend python,letesend-python,python letesend,python-letesend
Platform: UNKNOWN
Classifier: Development Status :: 3 - Alpha
Classifier: Intended Audience :: Developers
Classifier: Topic :: Software Development :: Build Tools
Classifier: License :: OSI Approved :: MIT License
Classifier: Programming Language :: Python :: 3
Classifier: Programming Language :: Python :: 3.4
Classifier: Programming Language :: Python :: 3.5
Classifier: Programming Language :: Python :: 3.6
License-File: LICENSE.txt
Requires-Dist: requests
